{"importBase":"import","nativeBase":"native","name":"resources","deps":["internal"],"uuids":["05cd6deef","090795574","096976e08","0ce1a6c63","40A5Nh9A9D05s+HugLwqBW","53dKTYrAZH6ZqgDnkYRHKS","98f4/0vrZBkIXEb+bpXTb1","98f4/0vrZBkIXEb+bpXTb1@6c48a","caTVvfLplDOYWzvHlybngg","caTVvfLplDOYWzvHlybngg@6c48a","caTVvfLplDOYWzvHlybngg@f9941","15Eg4srxNHeqZD+Bae7zGA","1aoIMoO9tMTrOEwz6cxCmd","1eL6cbkilPLLHpKsW9aqfd","20g1ukYUVPvKWKBRznAKo+","20g1ukYUVPvKWKBRznAKo+@6c48a","20g1ukYUVPvKWKBRznAKo+@f9941","3eklmdV0RG5a/fgK3DZgeb","3fhifeRpRAwoeRtJUnUeug","4c+R22JXlJkqQYRoufembo","54TknWPwVPqJqeCR+Y/Czo","54TknWPwVPqJqeCR+Y/Czo@6c48a","54TknWPwVPqJqeCR+Y/Czo@f9941","5dV3oiqfxMnbkXoYo3pGva","6cAm3u8bdMrbq56dLbjX9j","77DMvjH6xCnLojvw91Msqm","7dj5uJT9FMn6OrOOx83tfK","7dj5uJT9FMn6OrOOx83tfK@6c48a","7dj5uJT9FMn6OrOOx83tfK@f9941","8cuks/EaZE5ac8Tc6P131/","95EkngnxZFbYuFpsqVTaFr","95EkngnxZFbYuFpsqVTaFr@6c48a","95EkngnxZFbYuFpsqVTaFr@f9941","97QvudOu1H94YtFlIUJm+i","98f4/0vrZBkIXEb+bpXTb1@f9941","d7M58dRZJMv6XJWRVEi5X5","d7gonm48dC7p9GJH1CuViW","d8zUkVTadI1JIEPslzTJk2","e0NT+jAvFMX76TaDPwq8R/","e2xbxU3VlMOrknc4fnTjlN","f0g6KT7I9AQ6UD2NV7bvnY","fdoJXLgx1GAa2UhGATlj3o"],"paths":{"4":["ui/UIGuide",2],"5":["testui/UIA",2],"6":["texture/bg1",3],"7":["texture/bg1/texture",4,1],"8":["texture/finger",3],"9":["texture/finger/texture",4,1],"10":["texture/finger/spriteFrame",5,1],"11":["testui/UIB",2],"12":["data/tbcitymap",0],"13":["ui/UITipMsg",2],"17":["testui/UIPopUp",2],"18":["sound/click",1],"19":["testui/UIUIMgr",2],"23":["sound/bgm1",1],"24":["sound/bomb",1],"25":["testui/UIAudioMgr",2],"29":["ui/Shade",2],"33":["data/tbdemogroupdefinefromexcel",0],"34":["texture/bg1/spriteFrame",5,1],"35":["ui/UIHUD",2],"36":["testui/UIC",2],"37":["data/tbdemogroupdefinefromexcel1",0],"38":["testui/UIGuideTest1",2],"39":["testui/UIGuideTest2",2],"40":["sound/bgm2",1]},"scenes":{},"packs":{"05cd6deef":["27","21","7","15","31","9"],"090795574":["26","20","6","14","30","8"],"096976e08":["4","10"],"0ce1a6c63":["16","5","22","28","32"]},"versions":{"import":[],"native":[]},"redirect":[41,"0"],"debug":false,"extensionMap":{},"types":["cc.JsonAsset","cc.AudioClip","cc.Prefab","cc.ImageAsset","cc.Texture2D","cc.SpriteFrame"]}