{
  "__version__": "1.0.0",
  "current-scene": "500358d9-913e-44b8-9eb4-7c9ecc360452",
  "gizmos-infos": {
    "is2D": true,
    "is3DIcon": false,
    "iconSize": 2,
    "gridVisible": true,
    "gridColor": [
      150,
      150,
      150,
      255
    ],
    "isIconGizmo3D": false,
    "iconGizmoSize": 2,
    "isGridVisible": true
  },
  "camera-infos": {
    "f46876e4-e81b-4931-b493-6d367be385e7": {
      "position": {
        "x": 0,
        "y": 0,
        "z": 5000
      },
      "rotation": {
        "x": 0,
        "y": 0,
        "z": 0,
        "w": 1
      },
      "viewCenter": {
        "x": 0,
        "y": 0,
        "z": 0
      }
    },
    "726e5630-312f-4c6c-b8be-8b9a51d9881c": {
      "position": {
        "x": 640,
        "y": 360,
        "z": 5000
      },
      "rotation": {
        "x": 0,
        "y": 0,
        "z": 0,
        "w": 1
      },
      "viewCenter": {
        "x": 0,
        "y": 0,
        "z": 0
      }
    },
    "7c3e7fab-7b1e-4865-ba84-3cf81b48b9fb": {
      "position": {
        "x": 480.00000000000006,
        "y": 320,
        "z": 5000
      },
      "rotation": {
        "x": 0,
        "y": 0,
        "z": 0,
        "w": 1
      },
      "viewCenter": {
        "x": 0,
        "y": 0,
        "z": 0
      }
    },
    "2a6f65ef-7a9c-408d-8f88-9f7a021e4c4b": {
      "position": {
        "x": 640,
        "y": 360,
        "z": 5000
      },
      "rotation": {
        "x": 0,
        "y": 0,
        "z": 0,
        "w": 1
      },
      "viewCenter": {
        "x": 0,
        "y": 0,
        "z": 0
      }
    },
    "500358d9-913e-44b8-9eb4-7c9ecc360452": {
      "position": {
        "x": 359.99999999999994,
        "y": 640,
        "z": 5000
      },
      "rotation": {
        "x": 0,
        "y": 0,
        "z": 0,
        "w": 1
      },
      "viewCenter": {
        "x": 0,
        "y": 0,
        "z": 0
      }
    }
  },
  "camera-uuids": [
    "500358d9-913e-44b8-9eb4-7c9ecc360452"
  ],
  "float-window": {
    "position": {
      "cc": {
        "Camera": {
          "dock": false,
          "top": null,
          "bottom": 10,
          "left": null,
          "right": 10
        }
      }
    }
  }
}
